LICENSE
MANIFEST.in
README.rst
setup.py
tox.ini
lemon_metadata.egg-info/PKG-INFO
lemon_metadata.egg-info/SOURCES.txt
lemon_metadata.egg-info/dependency_links.txt
lemon_metadata.egg-info/requires.txt
lemon_metadata.egg-info/top_level.txt
metadata/__init__.py
metadata/admin.py
metadata/context_processors.py
metadata/managers.py
metadata/models.py
metadata/options.py
metadata/querysets.py
metadata/settings.py
metadata/sites.py
metadata/urls.py
metadata/views.py
metadata/widgets.py
metadata/locale/ru/LC_MESSAGES/django.mo
metadata/locale/ru/LC_MESSAGES/django.po
metadata/management/__init__.py
metadata/management/commands/__init__.py
metadata/management/commands/sync_metadata.py
metadata/migrations/0001_initial.py
metadata/migrations/__init__.py
metadata/templates/metadata/sitemap.xml
metadata/templates/metadata/admin/change_form.html
metadata/templatetags/__init__.py
metadata/templatetags/metadata.py
tests/__init__.py
tests/runtests.sh
tests/settings.py
tests/settings_context_processors.py
tests/settings_django_admin.py
tests/settings_lemon_admin.py
tests/settings_options.py
tests/settings_sites.py
tests/settings_views.py
tests/test_context_processors/__init__.py
tests/test_context_processors/models.py
tests/test_context_processors/tests.py
tests/test_django_admin/__init__.py
tests/test_django_admin/models.py
tests/test_django_admin/tests.py
tests/test_django_admin/urls.py
tests/test_lemon_admin/__init__.py
tests/test_lemon_admin/models.py
tests/test_lemon_admin/tests.py
tests/test_lemon_admin/urls.py
tests/test_options/__init__.py
tests/test_options/models.py
tests/test_options/tests.py
tests/test_options/urls.py
tests/test_sites/__init__.py
tests/test_sites/admin.py
tests/test_sites/models.py
tests/test_sites/tests.py
tests/test_views/__init__.py
tests/test_views/models.py
tests/test_views/tests.py